{
    "folds": [
        {
            "loss": 0.7073997956116994,
            "accuracy": 0.6526666666666666,
            "weighted_precision": 1.0,
            "weighted_recall": 0.6526666666666666,
            "weighted_f1_score": 0.7898346107301332
        },
        {
            "loss": 0.24962640249729157,
            "accuracy": 0.8813333333333333,
            "weighted_precision": 1.0,
            "weighted_recall": 0.8813333333333333,
            "weighted_f1_score": 0.9369241672572644
        },
        {
            "loss": 0.24060054552555085,
            "accuracy": 0.891,
            "weighted_precision": 1.0,
            "weighted_recall": 0.891,
            "weighted_f1_score": 0.9423585404547858
        },
        {
            "loss": 0.1998936526576678,
            "accuracy": 0.918,
            "weighted_precision": 1.0,
            "weighted_recall": 0.918,
            "weighted_f1_score": 0.9572471324296142
        },
        {
            "loss": 0.5500864099661509,
            "accuracy": 0.719,
            "weighted_precision": 1.0,
            "weighted_recall": 0.719,
            "weighted_f1_score": 0.8365328679464805
        }
    ],
    "average": {
        "loss": 0.3895213612516721,
        "accuracy": 0.8124,
        "weighted_precision": 1.0,
        "weighted_recall": 0.8124,
        "weighted_f1_score": 0.8925794637636557
    },
    "std_dev": {
        "loss": 0.20225454783905403,
        "accuracy": 0.10613144889449333,
        "weighted_precision": 0.0,
        "weighted_recall": 0.10613144889449333,
        "weighted_f1_score": 0.06681922223794828
    }
}